include/mmcfilters/attributes/AreaComputer.hpp
include/mmcfilters/attributes/AttributeComputedIncrementally.hpp
include/mmcfilters/attributes/AttributeComputer.hpp
include/mmcfilters/attributes/AttributeFactory.hpp
include/mmcfilters/attributes/AttributeNames.hpp
include/mmcfilters/attributes/BitquadsComputer.hpp
include/mmcfilters/attributes/BoundingBoxComputer.hpp
include/mmcfilters/attributes/ComputerAttributeBasedBitQuads.hpp
include/mmcfilters/attributes/ComputerMSER.hpp
include/mmcfilters/attributes/GrayLevelStatsComputer.hpp
include/mmcfilters/attributes/MomentBasedAttributeComputer.hpp
include/mmcfilters/attributes/TreeTopologyComputer.hpp
include/mmcfilters/attributes/VolumeComputer.hpp
include/mmcfilters/contours/ContoursComputedIncrementally.hpp
include/mmcfilters/filters/AttributeFilters.hpp
include/mmcfilters/filters/AttributeOpeningPrimitivesFamily.hpp
include/mmcfilters/filters/ExtinctionValues.hpp
include/mmcfilters/filters/UltimateAttributeOpening.hpp
include/mmcfilters/trees/BuilderMorphologicalTreeByUnionFind.hpp
include/mmcfilters/trees/MorphologicalTree.hpp
include/mmcfilters/trees/MorphologicalTree.tpp
include/mmcfilters/trees/NodeMT.hpp
include/mmcfilters/trees/NodeMTArena.hpp
include/mmcfilters/trees/NodeRes.hpp
include/mmcfilters/trees/ResidualTree.hpp
include/mmcfilters/utils/AdjacencyRelation.hpp
include/mmcfilters/utils/Common.hpp
include/mmcfilters/utils/ComputerDerivatives.hpp
include/mmcfilters/utils/Image.hpp
include/mmcfilters/utils/PixelSetManager.hpp
include/mtlearn/core.hpp
lib/cmake/mmcfilters/mmcfiltersTargets-release.cmake
lib/cmake/mmcfilters/mmcfiltersTargets.cmake
lib/libmmcfilters_lib.a
lib/libmtlearn_core.a
mmcfilters.cpython-312-darwin.so
mtlearn/__init__.py
mtlearn/_mtlearn.cpython-312-darwin.so
mtlearn/datasets.py
mtlearn/layers/.ipynb_checkpoints/ConnectedFilterLayerBySingleThreshold-checkpoint.py
mtlearn/layers/ConnectedFilterLayer.py
mtlearn/layers/ConnectedFilterLayerBySingleThreshold.py
mtlearn-0.1.8.dist-info/METADATA
mtlearn-0.1.8.dist-info/WHEEL
mtlearn-0.1.8.dist-info/RECORD
