Metadata-Version: 2.2
Name: mtlearn
Version: 0.1.8
Summary: Morphological tree learning utilities built on top of mmcfilters
Author-Email: Wonder Alexandre Luz Alves <worderalexandre@gmail.com>
Classifier: Programming Language :: Python
Classifier: Programming Language :: C++
Classifier: Topic :: Scientific/Engineering :: Image Processing
Classifier: Operating System :: MacOS
Classifier: Operating System :: Microsoft :: Windows
Classifier: Operating System :: POSIX :: Linux
Requires-Python: >=3.9
Requires-Dist: mmcfilters>=0.1.24
Provides-Extra: torch
Requires-Dist: torch>=2.0; extra == "torch"
